<includes>

<include name="View_50_List">
	
<control type="group">
      <visible>Control.IsVisible(50)</visible>
		  <description>List View (id=50)</description>
			<animation type="TYPE" condition="Window.IsVisible(2001)" reversible="false">
			   <effect type="slide" end="-1500,0" time="200"/>
    	</animation>
			<animation type="TYPE" condition="!Window.IsVisible(2001)" reversible="false">
			   <effect type="slide" start="-1500,0" time="200"/>
    	</animation>		
	
		  <animation type="WindowClose">
        	<effect type="fade" time="300"/>
			    <effect type="slide" end="+1500,0" time="300"/>
    	</animation>
			<animation type="WindowOpen">
        	<effect type="fade" time="300"/>
			    <effect type="slide" start="+1500,0" time="300"/>
    	</animation>
<!--------------------------------------------------------------------------------------------->

	   <control type="group">
	       <posy>60</posy>
				  <visible allowhiddenfocus="true">[Window.IsActive(1) | Container.Content(Addons) | Container.Content(Albums) | Container.Content(Artists)] | Container.Content(Movies)]</visible>
			    <animation effect="fade" start="0" end="100" time="400" condition="Control.HasFocus(60) | Container.Scrolling">Conditional</animation>


		   </control>

			 <control type="image">
					 <posx>28</posx>
					 <posy>286</posy>
					 <width>40</width>
					 <height>40</height>
				   <texture flipy="true">down_arrow.png</texture>
				   <visible>Container(50).HasPrevious</visible>
				   <animation effect="fade" time="400">VisibleChange</animation>
			 </control>

			<control type="image">
					<posx>28</posx>
					<posy>556</posy>
					<width>40</width>
					<height>40</height>
				  <texture>down_arrow.png</texture>
				  <visible>Container(50).HasNext</visible>
				  <animation effect="fade" time="400">VisibleChange</animation>
			</control>


<!-- XXXXXXXXXXXXXXXXXXXXXXXXXXXXXXXXXXXXXXXXXXXXXXXXX     -->

				
			<control type="label">
					<label>films</label>
					<posx>70</posx>
					<posy>190</posy>
					<height>30</height>
					<width>750</width>
					<font>Home_header</font>
					<visible>Container.Content(Movies)</visible>
					<align>left</align>
			</control>
				
			<control type="label">
					<label>musique</label>
					<posx>70</posx>
					<posy>190</posy>
					<height>30</height>
					<width>750</width>
					<font>Home_header</font>
					<visible>Container.Content(Albums)</visible>
					<align>left</align>
			</control>
				
			<control type="label">
					<label>artistes</label>
					<posx>70</posx>
					<posy>190</posy>
					<height>30</height>
					<width>750</width>
					<font>Home_header</font>
					<visible>Container.Content(Artists)</visible>
					<align>left</align>
			</control>
						
			<control type="label">
					<label>tv</label>
					<posx>70</posx>
					<posy>190</posy>
					<height>30</height>
					<width>750</width>
					<font>Home_header</font>
					<visible>Container.Content(tvshows)</visible>
					<align>left</align>
			</control>
				

      <control type="label">
			    <label>[LOWERCASE]$INFO[ListItem.label2][/LOWERCASE]</label>
					<posx>360</posx>
					<posy>200</posy>
					<height>30</height>
					<width>750</width>
					<font>Home_sub_header</font>
					<align>left</align>
      </control>

      <control type="list" id="50">
	         <visible>!Container.Content(episodes) + !Container.Content(tvshows) + !Container.Content(movies) + !Container.Content(seasons)</visible>
			     <posx>55</posx>
			     <posy>285</posy>
			     <width>290</width>
			     <height>310</height>
			     <onleft>9000</onleft>
			     <onright>60</onright>
			     <onup>50</onup>
			     <ondown>50</ondown>
			     <pagecontrol>60</pagecontrol>
			     <viewtype label="List">List</viewtype>
			     <scrolltime>200</scrolltime>
			     <itemlayout width="350" height="38">
                <control type="label">
					             <posx>20</posx>
					             <width>280</width>
					             <font>Medium</font>
					             <label>$INFO[ListItem.Label]</label>
					             <textcolor>white</textcolor>
				        </control>
			     </itemlayout>
			     <focusedlayout width="350" height="38">
				        <control type="label">
					             <posx>20</posx>
					             <width>280</width>
					             <font>Medium</font>
					             <label>[COLOR Accent]$INFO[ListItem.Label][/COLOR]</label>
					             <animation effect="fade" start="100" end="50" condition="!Control.HasFocus(50)">Conditional</animation>
				        </control>
			     </focusedlayout>
      </control>

<!--
		  <control type="scrollbar" id="60">
			     <posx>878</posx>
			     <posy>34</posy>
			     <height>652</height>
			     <onleft>50</onleft>
			     <onright>9000</onright>
			     <visible allowhiddenfocus="true">Control.HasFocus(60) | Container.Scrolling</visible>
			     <animation effect="fade" start="0" end="100" time="400" condition="Control.HasFocus(60) | Container.Scrolling">Conditional</animation>
		  </control>

-->

<!--
		  <control type="image">
			     <posx>360</posx>
			     <posy>290</posy>
			     <width>800</width>
			     <height>316</height>
			     <fadetime>400</fadetime>
			     <aspectratio align="left" aligny="center">scale</aspectratio>
			     <texture fallback="">tile.png</texture>
			     <visible>!IsEmpty(ListItem.Icon) + !Container.Content(Artists)</visible>
			     <animation effect="fade" time="500"></animation>
		  </control>
-->


		  <control type="image">
			     <posx>360</posx>
			     <posy>290</posy>
			     <width>416</width>
			     <height>316</height>
			     <fadetime>400</fadetime>
			     <aspectratio align="left" aligny="center">scale</aspectratio>
			     <texture fallback="">$INFO[ListItem.Icon]</texture>
			     <visible>!IsEmpty(ListItem.Icon)</visible>
			     <animation effect="fade" time="500"></animation>
		   </control>

			<control type="image">
				    <posx>780</posx>
				    <posy>290</posy>
				    <width>600</width>
				    <height>316</height>
				    <texture fallback="">$INFO[ListItem.Property(Fanart_Image)]</texture>
				    <fadetime>400</fadetime>
				    <aspectratio scalediffuse="false">scale</aspectratio>
				    <animation effect="fade" time="500">VisibleChange</animation>
				    <visible>!Container.Scrolling</visible>
			</control>
<!--
			<control type="image">
				    <posx>700</posx>
				    <posy>340</posy>
				    <width>600</width>
				    <height>200</height>
				    <texture fallback="">other_textures/fast_scrolling.png</texture>
				    <fadetime>400</fadetime>
				    <aspectratio scalediffuse="false">keep</aspectratio>
				    <animation effect="fade" time="500">VisibleChange</animation>
				    <visible>Container.Scrolling</visible>
			</control>
-->

</control>


<control type="image" id="2">
			<description>top left bar</description>
			<posx>0</posx>
			<posy>0</posy>
			<width>20</width>
			<height>138</height>
			<texture>bar.png</texture>
			<animation effect="fade" time="400">WindowOpen</animation>
			<animation effect="fade" time="400">WindowClose</animation>
	    <visible>!container.content(episodes) + !container.content(songs)</visible>
</control>
</include>

</includes>
